thousandeyes_sdk/instant_tests/__init__.py
thousandeyes_sdk/instant_tests/py.typed
thousandeyes_sdk/instant_tests/api/__init__.py
thousandeyes_sdk/instant_tests/api/agent_to_agent_instant_tests_api.py
thousandeyes_sdk/instant_tests/api/agent_to_server_instant_tests_api.py
thousandeyes_sdk/instant_tests/api/api_instant_tests_api.py
thousandeyes_sdk/instant_tests/api/dns_server_instant_tests_api.py
thousandeyes_sdk/instant_tests/api/dns_trace_instant_tests_api.py
thousandeyes_sdk/instant_tests/api/dnssec_instant_tests_api.py
thousandeyes_sdk/instant_tests/api/ftp_server_instant_tests_api.py
thousandeyes_sdk/instant_tests/api/http_page_load_instant_tests_api.py
thousandeyes_sdk/instant_tests/api/http_server_instant_tests_api.py
thousandeyes_sdk/instant_tests/api/instant_tests_api.py
thousandeyes_sdk/instant_tests/api/sip_server_instant_tests_api.py
thousandeyes_sdk/instant_tests/api/voice_instant_tests_api.py
thousandeyes_sdk/instant_tests/api/web_transaction_instant_tests_api.py
thousandeyes_sdk/instant_tests/models/__init__.py
thousandeyes_sdk/instant_tests/models/agent_base.py
thousandeyes_sdk/instant_tests/models/agent_interfaces.py
thousandeyes_sdk/instant_tests/models/agent_response.py
thousandeyes_sdk/instant_tests/models/agent_to_agent_instant_test.py
thousandeyes_sdk/instant_tests/models/agent_to_agent_instant_test_request.py
thousandeyes_sdk/instant_tests/models/agent_to_agent_instant_test_response.py
thousandeyes_sdk/instant_tests/models/agent_to_agent_properties.py
thousandeyes_sdk/instant_tests/models/agent_to_agent_test_protocol.py
thousandeyes_sdk/instant_tests/models/agent_to_server_instant_test.py
thousandeyes_sdk/instant_tests/models/agent_to_server_instant_test_request.py
thousandeyes_sdk/instant_tests/models/agent_to_server_instant_test_response.py
thousandeyes_sdk/instant_tests/models/agent_to_server_properties.py
thousandeyes_sdk/instant_tests/models/api_client_authentication.py
thousandeyes_sdk/instant_tests/models/api_instant_test.py
thousandeyes_sdk_instant_tests-2.23.0.dist-info/licenses/LICENSE
thousandeyes_sdk_instant_tests-2.23.0.dist-info/licenses/NOTICE
thousandeyes_sdk_instant_tests-2.23.0.dist-info/METADATA
thousandeyes_sdk_instant_tests-2.23.0.dist-info/WHEEL
thousandeyes_sdk_instant_tests-2.23.0.dist-info/top_level.txt
thousandeyes_sdk_instant_tests-2.23.0.dist-info/RECORD
